dpy2_migration_helper/__init__.py
dpy2_migration_helper/__main__.py
dpy2_migration_helper/dataclasses.py
dpy2_migration_helper/utils.py
dpy2_migration_helper/visitor.py
dpy2_migration_helper-0.1.0a1.dist-info/entry_points.txt
dpy2_migration_helper-0.1.0a1.dist-info/LICENSE
dpy2_migration_helper-0.1.0a1.dist-info/WHEEL
dpy2_migration_helper-0.1.0a1.dist-info/METADATA
dpy2_migration_helper-0.1.0a1.dist-info/RECORD
