Metadata-Version: 2.1
Name: dpy2-migration-helper
Version: 0.1.0a1
Summary: Helper for d.py 1.x -> 2.x migrations.
Author: Jakub Kuczys
Requires-Python: >=3.8
Classifier: Intended Audience :: Developers
Classifier: License :: OSI Approved :: Apache Software License
Classifier: Operating System :: OS Independent
Classifier: Programming Language :: Python :: 3 :: Only
Classifier: Programming Language :: Python :: 3.8
Classifier: Programming Language :: Python :: 3.9
Classifier: Programming Language :: Python :: 3.10
Classifier: Programming Language :: Python :: 3.11
Requires-Dist: typing_extensions
Project-URL: Home, https://github.com/Jackenmen/dpy2-migration-helper
